{
    "comisiones": [
        "COMUNICACIONES..."
    ], 
    "fecha": "2013-03-04", 
    "firmantes": [
        "GARCIA LARRABURU, SILVINA MARCELA (FRENTE PARA LA VICTORIA - PJ) (RIO NEGRO)"
    ], 
    "id": "0169-D-2013", 
    "nombre": "Proyecto de resoluci\u00f3n 0169-D-2013", 
    "sumario": "EXPRESAR BENEPLACITO POR EL APORTE QUE REALIZA EL SITIO WEB TIEMPOPATAGONICO.COM AL BRINDAR INFORMACION ACTUALIZADA EN TIEMPO REAL SOBRE LOS EVENTOS CLIMATICOS RELEVANTES PARA TODOS LOS CIUDADANOS Y TURISTAS DE LA REGION PATAGONICA.", 
    "tipo": "de resoluci\u00f3n", 
    "tramite": null, 
    "url": "http://www1.hcdn.gov.ar/proyxml/expediente.asp?fundamentos=si&numexp=0169-D-2013"
}