{
    "comisiones": [
        "ACCION SOCIAL Y SALUD PUBLICA"
    ], 
    "fecha": "2013-03-11", 
    "firmantes": [
        "LINARES, MARIA VIRGINIA (GEN) (BUENOS AIRES)", 
        "PERALTA, FABIAN FRANCISCO (GEN) (SANTA FE)", 
        "MILMAN, GERARDO FABIAN (GEN) (BUENOS AIRES)", 
        "DUCLOS, OMAR ARNALDO (GEN) (BUENOS AIRES)"
    ], 
    "id": "0631-D-2013", 
    "nombre": "Proyecto de resoluci\u00f3n 0631-D-2013", 
    "sumario": "PEDIDO DE INFORMES AL PODER EJECUTIVO SOBRE DIVERSAS CUESTIONES RELACIONADAS CON LA IMPLEMENTACION DEL PROGRAMA NACIONAL DE PREVENCION DEL SUICIDIO.", 
    "tipo": "de resoluci\u00f3n", 
    "tramite": 7, 
    "url": "http://www1.hcdn.gov.ar/proyxml/expediente.asp?fundamentos=si&numexp=0631-D-2013"
}