{
    "comisiones": [
        "RELACIONES EXTERIORES Y CULTO"
    ], 
    "fecha": "2013-03-12", 
    "firmantes": [
        "FERREYRA, ARACELI (FRENTE PARA LA VICTORIA - PJ) (CORRIENTES)"
    ], 
    "id": "0666-D-2013", 
    "nombre": "Proyecto de declaraci\u00f3n 0666-D-2013", 
    "sumario": "EXPRESAR BENEPLACITO POR EL AUMENTO DE LA CONTRIBUCION ECONOMICA ANUAL DISPUESTA POR EL GOBIERNO NACIONAL A LA COMISION INTERAMERICANA DE DERECHOS HUMANOS.", 
    "tipo": "de declaraci\u00f3n", 
    "tramite": 8, 
    "url": "http://www1.hcdn.gov.ar/proyxml/expediente.asp?fundamentos=si&numexp=0666-D-2013"
}