{
    "comisiones": [
        "EDUCACION"
    ], 
    "fecha": "2013-03-21", 
    "firmantes": [
        "LINARES, MARIA VIRGINIA (GEN) (BUENOS AIRES)"
    ], 
    "id": "1253-D-2013", 
    "nombre": "Proyecto de declaraci\u00f3n 1253-D-2013", 
    "sumario": "EXPRESAR BENEPLACITO POR LOS 35 A\u00d1OS DE DOBLE ESCOLARIDAD EN LA ESCUELA PRIMARIA N\u00b0 3, DE LA CIUDAD DE PIGUE, PROVINCIA DE BUENOS AIRES.", 
    "tipo": "de declaraci\u00f3n", 
    "tramite": 15, 
    "url": "http://www1.hcdn.gov.ar/proyxml/expediente.asp?fundamentos=si&numexp=1253-D-2013"
}