{
    "comisiones": [
        "RELACIONES EXTERIORES Y CULTO"
    ], 
    "fecha": "2013-03-21", 
    "firmantes": [
        "LINARES, MARIA VIRGINIA (GEN) (BUENOS AIRES)", 
        "MILMAN, GERARDO FABIAN (GEN) (BUENOS AIRES)", 
        "PERALTA, FABIAN FRANCISCO (GEN) (SANTA FE)", 
        "ITURRASPE, NORA GRACIELA (UNIDAD POPULAR) (BUENOS AIRES)"
    ], 
    "id": "1258-D-2013", 
    "nombre": "Proyecto de resoluci\u00f3n 1258-D-2013", 
    "sumario": "PEDIDO DE INFORMES AL PODER EJECUTIVO SOBRE, DIVERSAS CUESTIONES RELACIONADAS CON LAS MISIONES COMERCIALES LLEVADAS ADELANTE DURANTE EL A\u00d1O 2012, CON LA REPUBLICA DE ANGOLA.", 
    "tipo": "de resoluci\u00f3n", 
    "tramite": 15, 
    "url": "http://www1.hcdn.gov.ar/proyxml/expediente.asp?fundamentos=si&numexp=1258-D-2013"
}