{
    "comisiones": [
        "ASUNTOS CONSTITUCIONALES", 
        "CULTURA"
    ], 
    "fecha": "2013-04-03", 
    "firmantes": [
        "BARCHETTA, OMAR SEGUNDO (PARTIDO SOCIALISTA) (SANTA FE)", 
        "CICILIANI, ALICIA MABEL (PARTIDO SOCIALISTA) (SANTA FE)", 
        "RASINO, ELIDA ELENA (PARTIDO SOCIALISTA) (SANTA FE)", 
        "CUCCOVILLO, RICARDO OSCAR (PARTIDO SOCIALISTA) (BUENOS AIRES)"
    ], 
    "id": "1513-D-2013", 
    "nombre": "Proyecto de ley 1513-D-2013", 
    "sumario": "CIUDAD DE SANTA FE DE LA VERA CRUZ, PROVINCIA DE SANTA FE. SE LA DECLARA CUNA DE LA CONSTITUCION Y CAPITAL NACIONAL DE LAS CONVENCIONES CONSTITUYENTES .", 
    "tipo": "de ley", 
    "tramite": 20, 
    "url": "http://www1.hcdn.gov.ar/proyxml/expediente.asp?fundamentos=si&numexp=1513-D-2013"
}