{
    "comisiones": [
        "RELACIONES EXTERIORES Y CULTO", 
        "SEGURIDAD INTERIOR"
    ], 
    "fecha": "2013-04-08", 
    "firmantes": [
        "GARRIDO, MANUEL (UCR) (CIUDAD de BUENOS AIRES)", 
        "MALDONADO, VICTOR HUGO (UCR) (CHACO)", 
        "STORANI, MARIA LUISA (UCR) (BUENOS AIRES)", 
        "VAQUIE, ENRIQUE ANDRES (UCR) (MENDOZA)", 
        "BENEDETTI, ATILIO FRANCISCO SALVADOR (UCR) (ENTRE RIOS)", 
        "ALBARRACIN, JORGE LUIS (UCR) (MENDOZA)", 
        "ALVAREZ, ELSA MARIA (UCR) (SANTA CRUZ)"
    ], 
    "id": "1663-D-2013", 
    "nombre": "Proyecto de resoluci\u00f3n 1663-D-2013", 
    "sumario": "PEDIDO DE INFORMES VERBALES AL MINISTRO DE RELACIONES EXTERIORES Y CULTO, SE\u00d1OR HECTOR TIMERMAN, Y AL DIRECTOR DE SEGURIDAD DE DICHO MINISTERIO, SE\u00d1OR ULISES KANDIKO, ANTE LA COMISION BICAMERAL DE FISCALIZACION DE LOS ORGANISMOS Y ACTIVIDADES DE INTELIGENCIA, SOBRE DIVERSAS CUESTIONES RELACIONADAS CON ESCUCHAS TELEFONICAS AL CANCILLER Y OTROS FUNCIONARIOS.", 
    "tipo": "de resoluci\u00f3n", 
    "tramite": 23, 
    "url": "http://www1.hcdn.gov.ar/proyxml/expediente.asp?fundamentos=si&numexp=1663-D-2013"
}