{
    "comisiones": [
        "OBRAS PUBLICAS", 
        "PETICIONES, PODERES Y REGLAMENTO", 
        "PRESUPUESTO Y HACIENDA"
    ], 
    "fecha": "2013-04-09", 
    "firmantes": [
        "BULLRICH, PATRICIA (UNION POR TODOS) (CIUDAD de BUENOS AIRES)", 
        "PINEDO, FEDERICO (PRO) (CIUDAD de BUENOS AIRES)", 
        "MILMAN, GERARDO FABIAN (GEN) (BUENOS AIRES)", 
        "PUCHETA, RAMONA (SOCIALISTA DEL MIJD) (BUENOS AIRES)", 
        "BROWN, CARLOS RAMON (FRENTE PERONISTA) (BUENOS AIRES)"
    ], 
    "id": "1728-D-2013", 
    "nombre": "Proyecto de ley 1728-D-2013", 
    "sumario": "EJECUCION DE OBRAS DE INFRAESTRUCTURA NECESARIAS PARA LOS PLANES HIDRAULICOS URBANOS. INCLUSION EN LOS CREDITOS QUE SE SOLICITEN A ORGANISMOS MULTILATERALES.", 
    "tipo": "de ley", 
    "tramite": 24, 
    "url": "http://www1.hcdn.gov.ar/proyxml/expediente.asp?fundamentos=si&numexp=1728-D-2013"
}