{
    "comisiones": [
        "RELACIONES EXTERIORES Y CULTO"
    ], 
    "fecha": "2013-05-07", 
    "firmantes": [
        "GIUBERGIA, MIGUEL ANGEL (UCR) (JUJUY)", 
        "FIAD, MARIO RAYMUNDO (UCR) (JUJUY)", 
        "PUERTA, FEDERICO RAMON (FRENTE PERONISTA) (MISIONES)", 
        "SCHMIDT LIERMANN, CORNELIA (PRO) (CIUDAD de BUENOS AIRES)", 
        "PORTELA, AGUSTIN ALBERTO (UCR) (CORRIENTES)", 
        "BULLRICH, PATRICIA (UNION POR TODOS) (CIUDAD de BUENOS AIRES)", 
        "ALVAREZ, ELSA MARIA (UCR) (SANTA CRUZ)", 
        "WAYAR, WALTER RAUL (FRENTE PERONISTA FEDERAL) (SALTA)", 
        "FORTE, ULISES UMBERTO JOSE (UCR) (LA PAMPA)", 
        "COSTA, EDUARDO RAUL (UCR) (SANTA CRUZ)", 
        "SCIUTTO, RUBEN DARIO (FRENTE PARA LA VICTORIA - PJ) (TIERRA DEL FUEGO)", 
        "GUCCIONE, JOSE DANIEL (FRENTE PARA LA VICTORIA - PJ) (MISIONES)", 
        "SOTO, GLADYS BEATRIZ (FRENTE PARA LA VICTORIA - PJ) (CHACO)"
    ], 
    "id": "2741-D-2013", 
    "nombre": "Proyecto de declaraci\u00f3n 2741-D-2013", 
    "sumario": "SOLICITAR AL PODER EJECUTIVO DISPONGA APOYAR LA INCLUSION DE LA REPUBLICA DE CHINA (TAIWAN) COMO MIEMBRO OBSERVADOR EN LA CONVENCION MARCO DE LAS NACIONES UNIDAS SOBRE EL CAMBIO CLIMATICO (CMNUCC).", 
    "tipo": "de declaraci\u00f3n", 
    "tramite": 43, 
    "url": "http://www1.hcdn.gov.ar/proyxml/expediente.asp?fundamentos=si&numexp=2741-D-2013"
}