{
    "comisiones": [
        "POBLACION Y DESARROLLO HUMANO"
    ], 
    "fecha": "2013-05-08", 
    "firmantes": [
        "GUZMAN, OLGA ELIZABETH (MOV POP NEUQUINO) (NEUQUEN)"
    ], 
    "id": "2836-D-2013", 
    "nombre": "Proyecto de resoluci\u00f3n 2836-D-2013", 
    "sumario": "EXPRESAR BENEPLACITO POR EL 81\u00b0 ANIVERSARIO DE LA LOCALIDAD DE VILLA LA ANGOSTURA, PROVINCIA DEL NEUQUEN, A CELEBRARSE EL DIA 15 DE MAYO DE 2013.", 
    "tipo": "de resoluci\u00f3n", 
    "tramite": 44, 
    "url": "http://www1.hcdn.gov.ar/proyxml/expediente.asp?fundamentos=si&numexp=2836-D-2013"
}