{
    "comisiones": [
        "LEGISLACION DEL TRABAJO", 
        "FAMILIA..."
    ], 
    "fecha": "2013-05-14", 
    "firmantes": [
        "CASELLES, GRACIELA MARIA (FRENTE PARA LA VICTORIA - PARTIDO BLOQUISTA) (SAN JUAN)"
    ], 
    "id": "3039-D-2013", 
    "nombre": "Proyecto de ley 3039-D-2013", 
    "sumario": "LICENCIA PARA TRABAJADORAS MADRES CON HIJO QUE TENGA SINDROME DE DOWN - LEY 24716 -. MODIFICACION DEL ARTICULO 1\u00b0, SOBRE EXTENSION DE LA LICENCIA.", 
    "tipo": "de ley", 
    "tramite": 48, 
    "url": "http://www1.hcdn.gov.ar/proyxml/expediente.asp?fundamentos=si&numexp=3039-D-2013"
}