{
    "comisiones": [
        "LEGISLACION DEL TRABAJO", 
        "LEGISLACION GENERAL"
    ], 
    "fecha": "2013-05-15", 
    "firmantes": [
        "YAG\u00dcE, LINDA CRISTINA (UCR) (NEUQUEN)"
    ], 
    "id": "3128-D-2013", 
    "nombre": "Proyecto de ley 3128-D-2013", 
    "sumario": "DIA DEL SINDICALISMO Y DEL DIRIGENTE SINDICAL ARGENTINO . SE ESTABLECE COMO TAL EL 29 DE DICIEMBRE DE CADA A\u00d1O.", 
    "tipo": "de ley", 
    "tramite": 49, 
    "url": "http://www1.hcdn.gov.ar/proyxml/expediente.asp?fundamentos=si&numexp=3128-D-2013"
}