{
    "comisiones": [
        "PREVENCION DE ADICCIONES...", 
        "SEGURIDAD INTERIOR"
    ], 
    "fecha": "2013-06-14", 
    "firmantes": [
        "CICILIANI, ALICIA MABEL (PARTIDO SOCIALISTA) (SANTA FE)", 
        "COMI, CARLOS MARCELO (COALICION CIVICA - ARI) (SANTA FE)", 
        "RASINO, ELIDA ELENA (PARTIDO SOCIALISTA) (SANTA FE)", 
        "BIELLA CALVET, BERNARDO JOSE (UDESO SALTA) (SALTA)", 
        "DONDA PEREZ, VICTORIA ANALIA (LIBRES DEL SUR) (BUENOS AIRES)"
    ], 
    "id": "4741-D-2013", 
    "nombre": "Proyecto de resoluci\u00f3n 4741-D-2013", 
    "sumario": "PEDIDO DE INFORMES AL PODER EJECUTIVO SOBRE DIVERSAS CUESTIONES RELACIONADAS CON EL ALLANAMIENTO DE UN CARGAMENTO DE COCA\u00cdNA OCULTO EN CAJAS DE LANGOSTINOS, QUE HABR\u00cdAN SIDO SECUESTRADOS EN LAS INSTALACIONES DE LA PLANTA PESQUERA POSEID\u00d3N DE LA CIUDAD DE PUERTO MADRYN, PROVINCIA DEL CHUBUT", 
    "tipo": "de resoluci\u00f3n", 
    "tramite": 71, 
    "url": "http://www1.hcdn.gov.ar/proyxml/expediente.asp?fundamentos=si&numexp=4741-D-2013"
}