{
    "comisiones": [
        "LEGISLACION PENAL", 
        "JUSTICIA", 
        "PRESUPUESTO Y HACIENDA"
    ], 
    "fecha": "2013-07-01", 
    "firmantes": [
        "RASINO, ELIDA ELENA (PARTIDO SOCIALISTA) (SANTA FE)", 
        "BARCHETTA, OMAR SEGUNDO (PARTIDO SOCIALISTA) (SANTA FE)", 
        "LINARES, MARIA VIRGINIA (GEN) (BUENOS AIRES)", 
        "CUCCOVILLO, RICARDO OSCAR (PARTIDO SOCIALISTA) (BUENOS AIRES)"
    ], 
    "id": "5016-D-2013", 
    "nombre": "Proyecto de ley 5016-D-2013", 
    "sumario": "UNIDAD FISCAL DE INVESTIGACION DE DELITOS INFORMATICOS. CREACION EN EL AMBITO DEL MINISTERIO PUBLICO FISCAL.", 
    "tipo": "de ley", 
    "tramite": 80, 
    "url": "http://www1.hcdn.gov.ar/proyxml/expediente.asp?fundamentos=si&numexp=5016-D-2013"
}