{
    "comisiones": [
        "RELACIONES EXTERIORES Y CULTO"
    ], 
    "fecha": "2013-07-04", 
    "firmantes": [
        "FADUL, LILIANA (PARTIDO FEDERAL FUEGUINO) (TIERRA DEL FUEGO)"
    ], 
    "id": "5119-D-2013", 
    "nombre": "Proyecto de declaraci\u00f3n 5119-D-2013", 
    "sumario": "EXPRESAR BENEPLACITO POR EL RESPALDO DE LOS INTEGRANTES DEL Y-8 A LA REANUDACION DEL DIALOGO ENTRE LA REPUBLICA ARGENTINA Y EL REINO UNIDO DE GRAN BRETA\u00d1A E IRLANDA DEL NORTE SOBRE LA SOBERANIA DE LAS ISLAS MALVINAS.", 
    "tipo": "de declaraci\u00f3n", 
    "tramite": 83, 
    "url": "http://www1.hcdn.gov.ar/proyxml/expediente.asp?fundamentos=si&numexp=5119-D-2013"
}