{
    "comisiones": [
        "RELACIONES EXTERIORES Y CULTO"
    ], 
    "fecha": "2013-07-04", 
    "firmantes": [
        "STOLBIZER, MARGARITA ROSA (GEN) (BUENOS AIRES)"
    ], 
    "id": "5133-D-2013", 
    "nombre": "Proyecto de resoluci\u00f3n 5133-D-2013", 
    "sumario": "PEDIDO DE INFORMES AL PODER EJECUTIVO SOBRE LAS NEGOCIACIONES Y AVANCES A NIVEL MUNDIAL Y REGIONAL EN RELACION A LA PROPUESTA DEL ALTO COMISIONADO DE LAS NACIONES UNIDAS PARA LOS REFUGIADOS - ACNUR - Y LOS DIFERENTES GOBIERNOS PARA EL REASENTAMIENTO DE REFUGIADOS SIRIOS EXPULSADOS TRAS EL CONFLICTO INTERNO DESATADO EN LA REPUBLICA ARABE SIRIA.", 
    "tipo": "de resoluci\u00f3n", 
    "tramite": 83, 
    "url": "http://www1.hcdn.gov.ar/proyxml/expediente.asp?fundamentos=si&numexp=5133-D-2013"
}