{
    "comisiones": [
        "COMUNICACIONES..."
    ], 
    "fecha": "2013-07-11", 
    "firmantes": [
        "BARRANDEGUY, RAUL ENRIQUE (FRENTE PARA LA VICTORIA - PJ) (ENTRE RIOS)", 
        "RIOS, LILIANA MARIA (FRENTE PARA LA VICTORIA - PJ) (ENTRE RIOS)"
    ], 
    "id": "5260-D-2013", 
    "nombre": "Proyecto de resoluci\u00f3n 5260-D-2013", 
    "sumario": "EXPRESAR REPUDIO POR LA DECISION ARBITRARIA DE LAS AUTORIDADES DE RADIO ACTIVA CONCORDIA , PROVINCIA DE ENTRE RIOS, DE CANCELAR LA RETRANSMISION DEL PROGRAMA LA MA\u00d1ANA CONDUCIDO POR EL PERIODISTA VICTOR HUGO MORALES.", 
    "tipo": "de resoluci\u00f3n", 
    "tramite": 87, 
    "url": "http://www1.hcdn.gov.ar/proyxml/expediente.asp?fundamentos=si&numexp=5260-D-2013"
}