{
    "comisiones": [
        "AGRICULTURA Y GANADERIA"
    ], 
    "fecha": "2013-07-31", 
    "firmantes": [
        "ARENA, CELIA ISABEL (FRENTE PARA LA VICTORIA - PJ) (SANTA FE)"
    ], 
    "id": "5523-D-2013", 
    "nombre": "Proyecto de resoluci\u00f3n 5523-D-2013", 
    "sumario": "EXPRESAR BENEPLACITO POR LA 69\u00b0 EDICION DE LA FIESTA NACIONAL DE LA AGRICULTURA Y DIA DEL AGRICULTOR , A REALIZARSE EL DIA 8 DE SEPTIEMBRE DE 2013 EN LA CIUDAD DE ESPERANZA, PROVINCIA DE SANTA FE.", 
    "tipo": "de resoluci\u00f3n", 
    "tramite": 101, 
    "url": "http://www1.hcdn.gov.ar/proyxml/expediente.asp?fundamentos=si&numexp=5523-D-2013"
}