{
    "comisiones": [
        "EDUCACION", 
        "PRESUPUESTO Y HACIENDA"
    ], 
    "fecha": "2013-08-05", 
    "firmantes": [
        "KUNKEL, CARLOS MIGUEL (FRENTE PARA LA VICTORIA - PJ) (BUENOS AIRES)", 
        "GROSSO, LEONARDO (FRENTE PARA LA VICTORIA - PJ) (BUENOS AIRES)", 
        "BIDEGAIN, GLORIA (FRENTE PARA LA VICTORIA - PJ) (BUENOS AIRES)", 
        "GIANNETTASIO, GRACIELA MARIA (FRENTE PARA LA VICTORIA - PJ) (BUENOS AIRES)", 
        "RECALDE, HECTOR PEDRO (FRENTE PARA LA VICTORIA - PJ) (BUENOS AIRES)", 
        "CONTI, DIANA BEATRIZ (FRENTE PARA LA VICTORIA - PJ) (BUENOS AIRES)", 
        "SEGARRA, ADELA ROSA (FRENTE PARA LA VICTORIA - PJ) (BUENOS AIRES)", 
        "PUIGGROS, ADRIANA VICTORIA (FRENTE PARA LA VICTORIA - PJ) (BUENOS AIRES)", 
        "GARCIA, ANDREA FABIANA (FRENTE PARA LA VICTORIA - PJ) (BUENOS AIRES)", 
        "RAIMUNDI, CARLOS ALBERTO (FRENTE NUEVO ENCUENTRO) (BUENOS AIRES)", 
        "GARCIA, MARIA TERESA (FRENTE PARA LA VICTORIA - PJ) (BUENOS AIRES)", 
        "CALCAGNO Y MAILLMAN, ERIC (FRENTE PARA LA VICTORIA - PJ) (BUENOS AIRES)", 
        "FELETTI, ROBERTO JOSE (FRENTE PARA LA VICTORIA - PJ) (CIUDAD de BUENOS AIRES)", 
        "GRANADOS, DULCE (FRENTE PARA LA VICTORIA - PJ) (BUENOS AIRES)"
    ], 
    "id": "5588-D-2013", 
    "nombre": "Proyecto de ley 5588-D-2013", 
    "sumario": "UNIVERSIDAD NACIONAL RA\u00daL SCALABRINI ORTIZ CON SEDE EN LA CIUDAD DE SAN ISIDRO, PROVINCIA DE BUENOS AIRES. CREACION.", 
    "tipo": "de ley", 
    "tramite": 104, 
    "url": "http://www1.hcdn.gov.ar/proyxml/expediente.asp?fundamentos=si&numexp=5588-D-2013"
}