{
    "comisiones": [
        "ENERGIA Y COMBUSTIBLES"
    ], 
    "fecha": "2013-08-21", 
    "firmantes": [
        "BIANCHI, IVANA MARIA (FRENTE PERONISTA) (SAN LUIS)"
    ], 
    "id": "5842-D-2013", 
    "nombre": "Proyecto de resoluci\u00f3n 5842-D-2013", 
    "sumario": "EXPRESAR PREOCUPACION POR EL COMUNICADO DE LA SECRETARIA DE ENERGIA DE LA NACION, DONDE PIDEN PERMISO A LAS EMPRESAS PARA REVELAR PARTE DE LOS DATOS SENSIBLES QUE LAS MISMAS LE ENVIAN, PARA REENVIARSELOS A CONSULTORES PRIVADOS.", 
    "tipo": "de resoluci\u00f3n", 
    "tramite": 115, 
    "url": "http://www1.hcdn.gov.ar/proyxml/expediente.asp?fundamentos=si&numexp=5842-D-2013"
}