{
    "comisiones": [], 
    "fecha": "2013-08-23", 
    "firmantes": [
        "FORTUNA, FRANCISCO JOSE (CORDOBA FEDERAL) (CORDOBA)"
    ], 
    "id": "5912-D-2013", 
    "nombre": "Proyecto de resoluci\u00f3n 5912-D-2013", 
    "sumario": "EXPRESAR RECHAZO POR LA DECISION DEL ORGANISMO REGULADOR DEL SISTEMA NACIONAL DE AEROPUERTOS - ORSNA - , DONDE PROHIBE A LA EMPRESA LAN ARGENTINA , OCUPAR EL HANGAR QUE ACTUALMENTE UTILIZA EN EL AEROPARQUE METROPOLITANO Y CITAR A SU PRESIDENTE, SR. GUSTAVO LIPOVICH ANTE LAS COMISIONES DE TRANSPORTE, ECONOMIAS Y DESARROLLO REGIONAL, COMERCIO Y TURISMO, A FIN DE DAR LAS RAZONES DE TAL DECISION. (5912-D-2013) TRANSPORTES / ECONOMIAS Y DESARROLLO REGIONAL / COMERCIO / TURISMO", 
    "tipo": "de resoluci\u00f3n", 
    "tramite": 117, 
    "url": "http://www1.hcdn.gov.ar/proyxml/expediente.asp?fundamentos=si&numexp=5912-D-2013"
}