{
    "comisiones": [
        "ACCION SOCIAL Y SALUD PUBLICA"
    ], 
    "fecha": "2013-08-27", 
    "firmantes": [
        "MARTINEZ, JULIO CESAR (UCR) (LA RIOJA)"
    ], 
    "id": "6001-D-2013", 
    "nombre": "Proyecto de resoluci\u00f3n 6001-D-2013", 
    "sumario": "DECLARAR DE INTERES DE LA H. CAMARA EL XLII CONGRESO ARGENTINO DE GENETICA , A REALIZARSE DEL 20 AL 23 DE OCTUBRE DE 2013 EN LA PROVINCIA DE SALTA.", 
    "tipo": "de resoluci\u00f3n", 
    "tramite": 119, 
    "url": "http://www1.hcdn.gov.ar/proyxml/expediente.asp?fundamentos=si&numexp=6001-D-2013"
}