{
    "comisiones": [
        "DERECHOS HUMANOS Y GARANTIAS"
    ], 
    "fecha": "2013-09-13", 
    "firmantes": [
        "RAIMUNDI, CARLOS ALBERTO (FRENTE NUEVO ENCUENTRO) (BUENOS AIRES)", 
        "CHIENO, MARIA ELENA PETRONA (FRENTE PARA LA VICTORIA - PJ) (CORRIENTES)", 
        "ITURRASPE, NORA GRACIELA (UNIDAD POPULAR) (BUENOS AIRES)", 
        "LINARES, MARIA VIRGINIA (GEN) (BUENOS AIRES)", 
        "BRAWER, MARA (FRENTE PARA LA VICTORIA - PJ) (CIUDAD de BUENOS AIRES)"
    ], 
    "id": "6506-D-2013", 
    "nombre": "Proyecto de resoluci\u00f3n 6506-D-2013", 
    "sumario": "DECLARAR DE INTERES DE LA H. CAMARA EL PARLAMENTO FEDERAL JUVENIL , ORGANIZADO POR EL INSTITUTO NACIONAL CONTRA LA DISCRIMINACI\u00d3N, LA XENOFOBIA Y EL RACISMO (INADI) Y EL CONSEJO FEDERAL DE POL\u00cdTICAS P\u00daBLICAS ANTIDISCRIMINATORIAS, DURANTE EL A\u00d1O 2013.", 
    "tipo": "de resoluci\u00f3n", 
    "tramite": 133, 
    "url": "http://www1.hcdn.gov.ar/proyxml/expediente.asp?fundamentos=si&numexp=6506-D-2013"
}