{
    "comisiones": [
        "ACCION SOCIAL Y SALUD PUBLICA"
    ], 
    "fecha": "2013-09-18", 
    "firmantes": [
        "LEVERBERG, STELLA MARIS (FRENTE PARA LA VICTORIA - PJ) (MISIONES)"
    ], 
    "id": "6578-D-2013", 
    "nombre": "Proyecto de resoluci\u00f3n 6578-D-2013", 
    "sumario": "EXPRESAR BENEPLACITO POR LAS XI JORNADAS FEDERALES Y X INTERNACIONALES DE POLITICA, ECONOMIA Y GESTION DE MEDICAMENTOS , A REALIZARSE LOS DIAS 19 Y 20 DE SEPTIEMBRE DE 2013 EN LA CIUDAD DE POSADAS, PROVINCIA DE MISIONES.", 
    "tipo": "de resoluci\u00f3n", 
    "tramite": 136, 
    "url": "http://www1.hcdn.gov.ar/proyxml/expediente.asp?fundamentos=si&numexp=6578-D-2013"
}