{
    "fecha": "18/07/2007 20:20", 
    "votacion": {
        "AFIRMATIVO": [
            "acuna-kunz-juan", 
            "acuna-hugo-rodolfo", 
            "alarcon-maria-del-carmen", 
            "augsburger-silvia", 
            "azcoiti-pedro-jose", 
            "bayonzo-liliana-amelia", 
            "beccani-alberto-juan", 
            "bertol-paula-maria", 
            "binner-hermes", 
            "bisutti-delia-beatriz", 
            "burzaco-eugenio", 
            "cecco-carlos-jaime", 
            "chironi-fernando-gustavo", 
            "cittadini-stella", 
            "comelli-alicia-marcela", 
            "de-narvaez-francisco", 
            "dellepiane-carlos-francisco", 
            "fabris-luciano", 
            "ferro-francisco-jose", 
            "garcia-mendez-emilio", 
            "garcia-susana-rosa", 
            "giudici-silvana-myriam", 
            "godoy-juan-carlos", 
            "gonzalez-maria-america", 
            "gorbacz-leonardo-ariel", 
            "leguizamon-anibal-ernesto", 
            "leyba-de-marti-beatriz", 
            "lix-klett-roberto-ignacio", 
            "macaluse-eduardo-gabriel", 
            "martinez-raymonda-rafael", 
            "morini-pedro-juan", 
            "obiglio-julian-martin", 
            "perez-jose-adrian", 
            "pinedo-federico", 
            "quiroz-elsa-siria", 
            "ritondo-cristian", 
            "rodriguez-marcela-virginia", 
            "sanchez-fernando", 
            "storero-hugo", 
            "tate-alicia-ester", 
            "tinnirello-carlos-alberto", 
            "tonelli-pablo-gabriel", 
            "vanossi-jorge", 
            "zimmermann-victor"
        ], 
        "AUSENTE": [
            "abdala-josefina", 
            "accastello-eduardo", 
            "aguad-oscar-raul", 
            "alchouron-guillermo-eduardo", 
            "alonso-gumersindo-federico", 
            "alvarez-juan-jose", 
            "anauate-carlos-alfredo", 
            "ardid-mario-rolando", 
            "arnold-eduardo-ariel", 
            "baigorri-guillermo-francisco", 
            "baragiola-vilma-rosana", 
            "barrionuevo-jose-luis", 
            "bertone-rosana-andrea", 
            "bianchi-silvestre-marcela", 
            "bielsa-rafael", 
            "bonacorsi-juan-carlos", 
            "bonasso-miguel", 
            "borsani-luis-gustavo", 
            "bosch-de-sartori-irene-miriam", 
            "brillo-jose-ricardo", 
            "brue-daniel-agustin", 
            "bullrich-esteban", 
            "camano-dante", 
            "camano-eduardo-oscar", 
            "cambareri-fortunato-rafael", 
            "canteros-gustavo-jesus-adolfo", 
            "caserio-carlos-alberto", 
            "cassese-marina", 
            "cavadini-eduardo", 
            "collantes-genaro", 
            "colombi-ricardo", 
            "cordoba-jose-manuel", 
            "cornejo-alfredo-victor", 
            "costa-roberto-raul", 
            "cuevas-hugo-oscar", 
            "dalla-fontana-ariel", 
            "daud-jorge-carlos", 
            "de-brasi-marta-susana", 
            "de-marchi-omar-bruno", 
            "depetri-edgardo-fernando", 
            "di-landro-oscar-jorge", 
            "di-pollina-eduardo-alfredo", 
            "doga-maria-nelida", 
            "fernandez-alfredo-cesar", 
            "ferra-de-bartol-margarita", 
            "ferri-gustavo-enrique", 
            "franco-hugo-alberto", 
            "gallo-daniel-oscar", 
            "galvalisi-luis-alberto", 
            "garin-de-tula-lucia", 
            "ginzburg-nora", 
            "gioja-juan-carlos", 
            "giubergia-miguel-angel", 
            "gonzalez-jorge-pedro", 
            "gutierrez-francisco-virgilio", 
            "hernandez-cinthyia-gabriela", 
            "herrera-alberto", 
            "iglesias-roberto-raul", 
            "jano-ricardo-javier", 
            "jerez-esteban-eduardo", 
            "jerez-eusebia-antonia", 
            "kakubur-emilio", 
            "kroneberger-daniel-ricardo", 
            "lemme-maria-alicia", 
            "lemos-silvia", 
            "lorenzo-borocoto-eduardo", 
            "lozano-claudio-raul", 
            "lusquinos-luis-bernardo", 
            "macchi-carlos-guillermo", 
            "maffei-marta-olinda", 
            "mansur-nelida-mabel", 
            "marino-adriana-del-carmen", 
            "martinez-garbino-emilio", 
            "martinez-julio-cesar", 
            "martini-hugo", 
            "menem-eduardo-adrian", 
            "mongelo-jose-ricardo", 
            "montenegro-olinda", 
            "monti-lucrecia-etelvina", 
            "morandini-norma-elena", 
            "muller-mabel-hilda", 
            "naim-lidia-lucia", 
            "negri-mario-raul", 
            "nieva-alejandro-mario", 
            "oliva-cristian-rodolfo", 
            "oviedo-alejandra-beatriz", 
            "panzoni-patricia-ester", 
            "pastoriza-eduardo", 
            "perez-alberto-cesar", 
            "peso-stella-marys", 
            "poggi-claudio-javier", 
            "raimundi-carlos-alberto", 
            "richter-ana", 
            "rios-maria-fabiana", 
            "rodriguez-oscar-ernesto-r", 
            "rozas-angel", 
            "ruckauf-carlos-federico", 
            "salum-osvaldo-ruben", 
            "santander-mario", 
            "sarghini-jorge-emilio", 
            "sesma-laura-judith", 
            "sosa-carlos-alberto", 
            "storani-federico-teobaldo", 
            "tomaz-adriana-elisa", 
            "torino-hector-omar", 
            "torrontegui-maria-angelica", 
            "urtubey-juan-manuel", 
            "vargas-aignasse-geronimo", 
            "varisco-sergio-fausto", 
            "wilder-ricardo", 
            "zancada-pablo", 
            "zottos-miguel-andres-costas"
        ], 
        "NEGATIVO": [
            "aguero-elda-susana", 
            "alvarez-rodriguez-cristina", 
            "arriaga-julio-esteban", 
            "atanasof-alfredo-nestor", 
            "baladron-manuel-justo", 
            "bejarano-mario-fernando", 
            "berraute-ana", 
            "bianco-lia-fabiola", 
            "camano-graciela", 
            "canela-susana-mercedes", 
            "canevarolo-dante-omar", 
            "cantero-gutierrez-alberto", 
            "cantos-jose-maria", 
            "carlotto-remo-gerardo", 
            "carmona-maria-araceli", 
            "cesar-nora", 
            "chiacchio-nora-alicia", 
            "cigogna-luis-francisco-jorge", 
            "coirini-adriana-elsa", 
            "conti-diana-beatriz", 
            "cordoba-stella-maris", 
            "coscia-jorge-edmundo", 
            "daher-zulema-beatriz", 
            "daza-hector-ruben", 
            "de-bernardi-eduardo", 
            "de-la-barrera-guillermo", 
            "de-la-rosa-maria-graciela", 
            "delich-francisco", 
            "di-tullio-juliana", 
            "diaz-bancalari-jose-maria", 
            "diaz-roig-juan-carlos", 
            "diaz-susana-eladia", 
            "dovena-miguel-dante", 
            "fadel-patricia-susana", 
            "ferrigno-obarrio-santiago", 
            "figueroa-jose-oscar", 
            "fiol-paulina-esther", 
            "galantini-eduardo", 
            "garcia-de-moreno-eva", 
            "garcia-maria-teresa", 
            "garrido-arceo-jorge-antonio", 
            "genem-amanda-susana", 
            "giorgetti-jorge-raul", 
            "godoy-ruperto-eduardo", 
            "gonzalez-nancy-susana", 
            "gutierrez-graciela-beatriz", 
            "heredia-arturo-miguel", 
            "herrera-griselda-noemi", 
            "ilarregui-luis-alfredo", 
            "ingram-roddy-ernesto", 
            "irrazabal-juan-manuel", 
            "iturrieta-miguel-angel", 
            "kunkel-carlos-miguel", 
            "lamberto-oscar-santiago", 
            "landau-jorge-alberto", 
            "lauritto-jose-eduardo", 
            "lopez-amelia-de-los-milagros", 
            "lovaglio-saravia-antonio", 
            "marco-del-pont-mercedes", 
            "marconato-gustavo-angel", 
            "marino-juliana-isabel", 
            "massei-oscar-ermelindo", 
            "mediza-heriberto-eloy", 
            "mendez-de-ferreyra-araceli-estela", 
            "merino-raul-guillermo", 
            "moises-maria-carolina", 
            "monayar-ana-maria-carmen", 
            "moreno-carlos-julio", 
            "nemirovsci-osvaldo-mario", 
            "olmos-graciela-hortencia", 
            "osorio-marta-lucia", 
            "osuna-blanca-ines", 
            "perez-mirta", 
            "perie-hugo-ruben", 
            "porto-hector-norberto", 
            "recalde-hector-pedro", 
            "rico-maria-del-carmen-cecilia", 
            "rojkes-de-alperovich-beatriz-liliana", 
            "roman-carmen", 
            "romero-rosario", 
            "roquel-rodolfo", 
            "rossi-agustin-oscar", 
            "rosso-graciela-zulema", 
            "salim-juan-arturo", 
            "sartori-diego-horacio", 
            "sluga-juan-carlos", 
            "snopek-carlos-daniel", 
            "solanas-raul-patricio", 
            "soto-gladys-beatriz", 
            "spatola-paola-rosana", 
            "stella-anibal-jesus", 
            "sylvestre-begnis-juan-hector", 
            "thomas-enrique-luis", 
            "toledo-hugo-david", 
            "tulio-rosa-ester", 
            "unac-jose-ruben", 
            "vaca-narvaja-patricia", 
            "velarde-marta-sylvia", 
            "villaverde-jorge-antonio", 
            "west-mariano-federico"
        ]
    }, 
    "asunto": "Solicitud de Trat. s/Tablas del Dip. MACALUSE, Eduardo G."
}