{
    "url": "http://www.infoleg.gob.ar/infolegInternet/anexos/245000-249999/249221/norma.htm", 
    "nombre": "Movilidad de las asignaciones familiares", 
    "fecha": "2015", 
    "votacion": {
        "AFIRMATIVO": [], 
        "AUSENTE": [], 
        "ABSTENCION": [], 
        "NEGATIVO": []
    }, 
    "sumario": "LAS ASIGNACIONES FAMILIARES PREVISTAS EN LA LEY 24.714, SUS NORMAS COMPLEMENTARIAS Y MODIFICATORIAS, CON EXCEPCION DE LA ESTABLECIDA EN EL INCISO E) DEL ARTICULO 6\u00b0 DE LA LEY 24.714, SERAN MOVILES. EL CALCULO DEL INDICE DE MOVILIDAD SE REALIZARA CONFORME A LO PREVISTO EN EL ANEXO DE LA LEY 26.417. LA MOVILIDAD SE APLICARA AL MONTO DE LAS ASIGNACIONES FAMILIARES Y A LA ACTUALIZACION DE LOS RANGOS DE INGRESOS DEL GRUPO FAMILIAR QUE DETERMINAN EL COBRO, EN LOS CASOS EN QUE CORRESPONDE SU UTILIZACION. EN NINGUN CASO LA APLICACION DE DICHO INDICE PODRA PRODUCIR UNA DISMINUCION DEL VALOR DE LA ASIGNACION."
}