{
    "url": "http://www.infoleg.gob.ar/infolegInternet/anexos/215000-219999/215215/norma.htm", 
    "nombre": "Reforma del Consejo de la Magistratura", 
    "fecha": "2013-04-25", 
    "votacion": {
        "AFIRMATIVO": [
            "abdala-de-matarazzo-norma-amanda", 
            "aguirre-hilda-clelia", 
            "albrieu-oscar-edmundo-nicolas", 
            "alonso-maria-luz", 
            "arena-celia-isabel", 
            "arregui-andres-roberto", 
            "avoscan-herman-horacio", 
            "balcedo-maria-ester", 
            "barrandeguy-raul-enrique", 
            "barrionuevo-walter-basilio", 
            "basterra-luis-eugenio", 
            "bedano-nora-esther", 
            "bermejo-rolando-adolfo", 
            "bernal-maria-eugenia", 
            "bertone-rosana-andrea", 
            "biancalani-fabio-dario", 
            "bianchi-maria-del-carmen", 
            "bidegain-gloria-mercedes", 
            "blas-ines-imelda", 
            "bongiorno-maria-jose", 
            "brawer-mara", 
            "brillo-jose-ricardo", 
            "bromberg-isaac-benjamin", 
            "brue-daniel-agustin", 
            "cabral-salvador", 
            "calcagno-eric", 
            "carlotto-remo-gerardo", 
            "carmona-guillermo-ramon", 
            "carrillo-maria-del-carmen", 
            "caselles-graciela-maria", 
            "catalan-magni-julio-cesar", 
            "cejas-jorge-alberto", 
            "chieno-maria-elena", 
            "ciampini-jose-alberto", 
            "cigogna-luis-francisco-jorge", 
            "cleri-marcos", 
            "colazo-mario-jorge", 
            "comelli-alicia-marcela", 
            "conti-diana-beatriz", 
            "contrera-monica-graciela", 
            "cordoba-stella-maris", 
            "corradi-de-beltran-ana-maria", 
            "corregido-elena-mercedes", 
            "currilen-oscar-ruben", 
            "dato-alfredo-carlos", 
            "de-la-rosa-maria-graciela", 
            "de-pedro-eduardo-enrique", 
            "depetri-edgardo-fernando", 
            "di-tullio-juliana", 
            "diaz-bancalari-jose-maria", 
            "diaz-maria-rosa", 
            "diaz-roig-juan-carlos", 
            "donkin-carlos-guillermo", 
            "elorriaga-osvaldo-enrique", 
            "feletti-roberto-jose", 
            "felix-omar", 
            "fellner-liliana-beatriz", 
            "fernandez-anibal-domingo", 
            "fernandez-sagasti-anabel", 
            "ferra-de-bartol-margarita", 
            "ferreyra-araceli", 
            "filmus-daniel-fernando", 
            "fiore-vinuales-maria-cristina-del-valle", 
            "forconi-juan-carlos", 
            "francioni-fabian-marcelo", 
            "fuentes-marcelo-jorge", 
            "gallardo-miriam-graciela-del-valle", 
            "garcia-andrea-fabiana", 
            "garcia-larraburu-silvina-marcela", 
            "garcia-maria-teresa", 
            "gdansky-carlos-enrique", 
            "giaccone-claudia-alejandra", 
            "giacomino-daniel-oscar", 
            "giannettasio-graciela-maria", 
            "gimenez-sandra-daniela", 
            "godoy-ruperto-eduardo", 
            "gonzalez-juan-dante", 
            "gonzalez-nancy-susana", 
            "gonzalez-pablo-gerardo", 
            "granados-dulce", 
            "grosso-leonardo", 
            "guastavino-pedro-guillermo-angel", 
            "guccione-jose-daniel", 
            "guinle-marcelo-alejandro", 
            "gutierrez-monica-edith", 
            "guzman-olga-elizabeth", 
            "harispe-gaston", 
            "heller-carlos", 
            "herrera-griselda-noemi", 
            "herrera-jose-alberto", 
            "higonet-maria-de-los-angeles", 
            "ianni-ana-maria", 
            "irrazabal-juan-manuel", 
            "iturrez-de-capellini-ada-rosa", 
            "junio-juan-carlos-isaac", 
            "kosiner-pablo-francisco-juan", 
            "kunkel-carlos-miguel", 
            "labado-maria-ester", 
            "landau-jorge-alberto", 
            "larroque-andres", 
            "latorre-roxana-itati", 
            "leguizamon-maria-laura", 
            "leverberg-stella-maris", 
            "llanos-ermindo-edgardo-marcelo", 
            "lopez-osvaldo-ramon", 
            "lotto-de-vecchietti-ines-beatriz", 
            "luna-mirtha-maria-teresita", 
            "mansilla-sergio-francisco", 
            "martinez-oscar-ariel", 
            "mayans-jose-miguel-angel", 
            "mendoza-mayra-soledad", 
            "mendoza-sandra-marcela", 
            "metaza-mario-alfredo", 
            "molina-manuel-isauro", 
            "mongelo-jose-ricardo", 
            "moreno-carlos-julio", 
            "navarro-graciela", 
            "nebreda-carmen-rosa", 
            "oliva-cristian-rodolfo", 
            "oporto-mario-nestor", 
            "ortiz-correa-marcia-sara-maria", 
            "ortiz-mariela", 
            "pais-juan-mario", 
            "parrilli-nanci-maria-agustina", 
            "pastoriza-mirta-ameliana", 
            "perie-julia-argentina", 
            "perotti-omar-angel", 
            "perroni-ana-maria", 
            "persico-daniel-raul", 
            "pichetto-miguel-angel", 
            "pietragalla-corti-horacio", 
            "pilatti-vergara-maria-ines", 
            "puiggros-adriana-victoria", 
            "raimundi-carlos-alberto", 
            "recalde-hector-pedro", 
            "redczuk-oscar-felipe", 
            "regazzoli-maria-cristina", 
            "riofrio-marina-raquel", 
            "rios-liliana-maria", 
            "rios-roberto-fabian", 
            "risko-silvia-lucrecia", 
            "rivarola-ruben-armando", 
            "rivas-jorge", 
            "robledo-roberto-ricardo", 
            "rojkes-de-alperovich-beatriz-l", 
            "roldan-jose-maria", 
            "rossi-agustin-oscar", 
            "ruiz-aida-delia", 
            "ruiz-diaz-elsa-beatriz", 
            "salim-juan-arturo", 
            "santillan-walter-marcelo", 
            "sciutto-ruben-dario", 
            "segarra-adela-rosa", 
            "simoncini-silvia-rosa", 
            "solanas-julio-rodolfo-francisco", 
            "soto-gladys-beatriz", 
            "tineo-javier-hector", 
            "tomas-hector-daniel", 
            "unac-jose-ruben", 
            "vilarino-jose-antonio", 
            "villa-jose-antonio", 
            "wayar-walter-raul", 
            "yarade-rodolfo-fernando", 
            "yazbek-ruben-david", 
            "zamarreno-maria-eugenia", 
            "ziebart-cristina-isabel", 
            "ziegler-alex-roberto"
        ], 
        "AUSENTE": [
            "estenssoro-maria-eugenia", 
            "lores-horacio", 
            "meabe-de-matho-josefina-angelica", 
            "menem-carlos-saul", 
            "roberti-alberto-oscar", 
            "rodriguez-marcela-virginia", 
            "sabbatella-martin", 
            "valinotto-jorge-anselmo"
        ], 
        "ABSTENCION": [], 
        "NEGATIVO": [
            "aguad-oscar-raul", 
            "aguilar-lino-walter", 
            "albarracin-jorge-luis", 
            "alfonsin-ricardo-luis", 
            "alonso-gumersindo-federico", 
            "alonso-laura", 
            "alvarez-elsa-maria", 
            "alvarez-jorge-mario", 
            "amadeo-eduardo-pablo", 
            "argumedo-alcira-susana", 
            "artaza-eugenio-justiniano", 
            "aspiazu-lucio-bernardo", 
            "asseff-alberto-emilio", 
            "atanasof-alfredo-nestor", 
            "barbieri-mario-leandro", 
            "barchetta-omar-segundo", 
            "basualdo-roberto-gustavo", 
            "bazze-miguel-angel", 
            "benedetti-atilio-francisco-salvador", 
            "bertol-paula-maria", 
            "bianchi-ivana-maria", 
            "biella-calvet-bernardo-jose", 
            "blanco-de-peralta-blanca", 
            "borello-marta-teresita", 
            "brizuela-y-doria-de-cara-olga-ines", 
            "brown-carlos-ramon", 
            "bullrich-patricia", 
            "buryaile-ricardo", 
            "cabanchik-samuel-manuel", 
            "camano-graciela", 
            "cano-jose-manuel", 
            "cardelli-jorge-justo", 
            "carranza-carlos-alberto", 
            "carrio-elisa-maria-avelina", 
            "casanas-juan-francisco", 
            "castanon-hugo", 
            "castillo-oscar-anibal", 
            "chemes-jorge-omar", 
            "ciciliani-alicia-mabel", 
            "cimadevilla-mario-jorge", 
            "comi-carlos-marcelo", 
            "cortina-roy", 
            "costa-eduardo-raul", 
            "cremer-de-busti-maria-cristina", 
            "cuccovillo-ricardo-oscar", 
            "de-ferrari-rueda-patricia", 
            "de-gennaro-victor-norberto", 
            "de-marchi-omar-bruno", 
            "de-narvaez-francisco", 
            "de-prat-gay-alfonso", 
            "di-perna-graciela-agustina", 
            "donda-perez-victoria-analia", 
            "duclos-omar-arnaldo", 
            "escudero-sonia-margarita", 
            "espindola-gladys-susana", 
            "fadul-liliana", 
            "faustinelli-hipolito", 
            "favario-carlos-alberto", 
            "fernandez-rodolfo-alfredo", 
            "ferrari-gustavo-alfredo", 
            "fiad-mario-raymundo", 
            "forte-ulises-umberto", 
            "fortuna-francisco-jose", 
            "gambaro-natalia", 
            "garnero-estela-ramona", 
            "garramuno-jorge-alberto", 
            "garrido-manuel", 
            "germano-daniel", 
            "gil-lavedra-ricardo-rodolfo", 
            "giubergia-miguel-angel", 
            "giustiniani-ruben-hector", 
            "gonzalez-gladys-esther", 
            "ibarra-eduardo-mauricio", 
            "iturraspe-nora-graciela", 
            "juez-luis-alfredo", 
            "juri-mariana", 
            "kroneberger-daniel-ricardo", 
            "ledesma-julio-ruben", 
            "linares-jaime", 
            "linares-maria-virginia", 
            "lozano-claudio-raul", 
            "majdalani-silvia-cristina", 
            "maldonado-hugo", 
            "marino-juan-carlos", 
            "martinez-alfredo-anselmo", 
            "martinez-ernesto-felix", 
            "martinez-julio-cesar", 
            "martinez-soledad", 
            "mazzarella-susana-del-valle", 
            "michetti-marta-gabriela", 
            "milman-gerardo-fabian", 
            "molas-pedro-omar", 
            "monllau-blanca-maria-del-valle", 
            "montero-laura-gisela", 
            "morales-gerardo-ruben", 
            "morandini-norma-elena", 
            "mouilleron-roberto-mario", 
            "moyano-juan-facundo", 
            "muller-edgar-raul", 
            "muller-mabel-hilda", 
            "negre-de-alonso-liliana-teresita", 
            "negri-mario-raul", 
            "nikisch-roy-abelardo", 
            "obiglio-julian-martin", 
            "ocana-maria-graciela", 
            "olmedo-alfredo-horacio", 
            "orsolini-pablo-eduardo", 
            "pansa-sergio-horacio", 
            "parada-liliana-beatriz", 
            "peralta-fabian-francisco", 
            "perez-alberto-jose", 
            "perez-alsina-juan-agustin", 
            "petcoff-naidenoff-luis-carlos", 
            "piemonte-hector-horacio", 
            "pinedo-federico", 
            "plaini-francisco-omar", 
            "portela-agustin-alberto", 
            "pradines-roberto-arturo", 
            "pucheta-ramona", 
            "puerta-federico-ramon", 
            "rached-emilio-alberto", 
            "rasino-elida-elena", 
            "re-hilma-leonor", 
            "reutemann-carlos-alberto", 
            "riestra-antonio-sabino", 
            "rivara-raul-alberto", 
            "rodriguez-saa-adolfo", 
            "rogel-fabian-dulio", 
            "romero-juan-carlos", 
            "rucci-claudia-monica", 
            "sacca-luis-fernando", 
            "santin-eduardo", 
            "sanz-ernesto-ricardo", 
            "schmidt-liermann-cornelia", 
            "sola-felipe-carlos", 
            "solanas-fernando-ezequiel", 
            "stolbizer-margarita-rosa", 
            "storani-maria-luisa", 
            "terada-alicia", 
            "thomas-enrique-luis", 
            "tonelli-pablo-gabriel", 
            "triaca-alberto-jorge", 
            "tunessi-juan-pedro", 
            "vaquie-enrique-andres", 
            "veaute-mariana-alejandra", 
            "vera-arturo", 
            "verani-pablo", 
            "verna-carlos-alberto", 
            "videla-nora-esther", 
            "villata-graciela-susana", 
            "yague-linda-cristina", 
            "yoma-jorge-raul", 
            "zabalza-juan-carlos"
        ]
    }, 
    "sumario": "MODIFICACION DE LAS LEYES N\u00b0 24.937, 11.672, 19.362, 17.928, 23.853, 24.156 Y 26.376."
}